README.md
setup.py
azure_logging/__init__.py
azure_logging.egg-info/PKG-INFO
azure_logging.egg-info/SOURCES.txt
azure_logging.egg-info/dependency_links.txt
azure_logging.egg-info/top_level.txt
test/test_file.py