Metadata-Version: 2.1
Name: azure-logging
Version: 0.0.1
Summary: Template for PyPI packages
Home-page: 
Requires-Python: >=3.8
